{"placements":[{"x":808,"y":467},{"x":808,"y":337},{"x":808,"y":437},{"x":808,"y":417},{"x":798,"y":467},{"x":628,"y":467},{"x":808,"y":367},{"x":798,"y":337},{"x":808,"y":377},{"x":808,"y":457},{"x":808,"y":447},{"x":808,"y":427},{"x":608,"y":467},{"x":618,"y":337},{"x":608,"y":457},{"x":618,"y":457},{"x":608,"y":337},{"x":798,"y":407},{"x":618,"y":467},{"x":638,"y":337},{"x":728,"y":467},{"x":628,"y":337},{"x":798,"y":357},{"x":798,"y":367},{"x":788,"y":337},{"x":768,"y":467},{"x":658,"y":337},{"x":668,"y":337},{"x":638,"y":467},{"x":798,"y":387},{"x":718,"y":467},{"x":608,"y":347},{"x":778,"y":447},{"x":798,"y":347},{"x":618,"y":347},{"x":648,"y":457},{"x":628,"y":447},{"x":808,"y":407},{"x":648,"y":337},{"x":788,"y":357},{"x":678,"y":467},{"x":608,"y":447},{"x":778,"y":337},{"x":798,"y":427},{"x":698,"y":467},{"x":628,"y":457},{"x":808,"y":357},{"x":608,"y":427},{"x":628,"y":347},{"x":608,"y":437},{"x":748,"y":457},{"x":658,"y":467},{"x":648,"y":467},{"x":808,"y":387},{"x":738,"y":457},{"x":788,"y":347},{"x":638,"y":457},{"x":788,"y":457},{"x":788,"y":377},{"x":738,"y":467},{"x":658,"y":457},{"x":808,"y":397},{"x":668,"y":467},{"x":758,"y":467},{"x":768,"y":337},{"x":798,"y":417},{"x":678,"y":337},{"x":638,"y":447},{"x":618,"y":447},{"x":718,"y":457}]}
